setup.py
src/RB2_NRL.py
src/active_pulses.py
src/awp.py
src/basic_pulses.py
src/cb.py
src/create_random_list.py
src/edges.py
src/gates.py
src/global_var.py
src/moderator.py
src/operations.py
src/predistortion.py
src/predistortion_backup.py
src/predistortion_backup_new_pred.py
src/pulses.py
src/rb.py
src/rb2.py
src/rule.py
src/rule2.py
src/shapes.py
src/share.py
src/simple_pulses.py
src/slepian.py
src/xeb.py
src/xeb_cliford.py
pulsegen-0.0.1.dist-info/METADATA
pulsegen-0.0.1.dist-info/WHEEL
pulsegen-0.0.1.dist-info/licenses/LICENSE.txt
pulsegen-0.0.1.dist-info/RECORD
